setup.py
distr_12.egg-info/PKG-INFO
distr_12.egg-info/SOURCES.txt
distr_12.egg-info/dependency_links.txt
distr_12.egg-info/not-zip-safe
distr_12.egg-info/top_level.txt
distributions/Binomialdistribution.py
distributions/Gaussiandistribution.py
distributions/Generaldistribution.py
distributions/__init__.py