Metadata-Version: 1.0
Name: distr-12
Version: 0.1
Summary: Gaussian distributions
Home-page: UNKNOWN
Author: Erwin
Author-email: erwinhuang16@gmail.com
License: UNKNOWN
Platform: UNKNOWN
